 {
    "localIP": "1.37.67.132",
    "publicIP": "1.37.67.132",
    "ip": "1.37.67.132",
    "latitude": "14.6084",
    "longitude": "120.9753",
    "address": "Abad Santos Avenue",
    "house_number": "1315",
    "neighbourhood": "",
    "city": "Manila",
    "county": "",
    "region": "",
    "country": "Philippines",
    "postal": "1003",
    "display_name": "1315, Abad Santos Avenue, Barangay 238, Tondo, Second District, Manila, Capital District, Metro Manila, 1003, Philippines",
    "importance": 0
}